vapix_python/GeolocationAPI.py
vapix_python/PTZControl.py
vapix_python/VapixAPI.py
vapix_python-0.0.1.dist-info/METADATA
vapix_python-0.0.1.dist-info/WHEEL
vapix_python-0.0.1.dist-info/top_level.txt
vapix_python-0.0.1.dist-info/RECORD
